flask_multipass_cern.py
flask_multipass_cern-2.3.dist-info/METADATA
flask_multipass_cern-2.3.dist-info/WHEEL
flask_multipass_cern-2.3.dist-info/entry_points.txt
flask_multipass_cern-2.3.dist-info/licenses/LICENSE
flask_multipass_cern-2.3.dist-info/RECORD
