Metadata-Version: 2.4
Name: Flask-Multipass-CERN
Version: 2.3
Summary: CERN-specific Flask-Multipass providers
Project-URL: GitHub, https://github.com/indico/flask-multipass-cern
Author-email: Indico Team <indico-team@cern.ch>
License-Expression: MIT
License-File: LICENSE
Requires-Python: ~=3.9
Requires-Dist: flask-multipass[authlib]>=0.4.3
Requires-Dist: urllib3>=1.26.0
Provides-Extra: dev
Requires-Dist: freezegun; extra == 'dev'
Requires-Dist: httpretty; extra == 'dev'
Requires-Dist: pytest; extra == 'dev'
Requires-Dist: pytest-mock; extra == 'dev'
Requires-Dist: ruff; extra == 'dev'
